codesecindirectmitgpl3/__init__.py
codesecindirectmitgpl3/module1.py
codesecindirectmitgpl3-0.1.0.dist-info/LICENSE
codesecindirectmitgpl3-0.1.0.dist-info/METADATA
codesecindirectmitgpl3-0.1.0.dist-info/WHEEL
codesecindirectmitgpl3-0.1.0.dist-info/top_level.txt
codesecindirectmitgpl3-0.1.0.dist-info/RECORD
